medberg/__init__.py
medberg/exceptions.py
medberg/file.py
medberg/securesite.py
medberg-1.3.0.dist-info/licenses/LICENSE
medberg-1.3.0.dist-info/METADATA
medberg-1.3.0.dist-info/WHEEL
medberg-1.3.0.dist-info/top_level.txt
medberg-1.3.0.dist-info/RECORD
