Metadata-Version: 2.4
Name: medberg
Version: 1.3.0
Summary: Download files from the Cencora secure file transfer site
Author-email: Eddie Cosma <eddie.cosma@gmail.com>
Project-URL: Homepage, https://github.com/eddie-cosma/medberg
Project-URL: Issues, https://github.com/eddie-cosma/medberg/issues
Keywords: amerisource,cencora
Classifier: Programming Language :: Python :: 3
Classifier: License :: OSI Approved :: MIT License
Classifier: Operating System :: OS Independent
Requires-Python: >=3.10
License-File: LICENSE
Requires-Dist: beautifulsoup4>=4.13.0
Provides-Extra: dev
Requires-Dist: black==25.1.0; extra == "dev"
Requires-Dist: pytest; extra == "dev"
Requires-Dist: python-dotenv; extra == "dev"
Dynamic: license-file
